{
  "code": 200,
  "msg": "操作成功",
  "data": {
    "pageNum": 1,
    "pageSize": 1,
    "total": 1,
    "totalPages": 0,
    "list": [
      {
        "mmsi": "352361000",
        "vesselEnName": "MSC BETTINA",
        "vesselCnName": "地中海贝蒂娜",
        "vesselCode": "MSCET",
        "vesselUnCode": "UN9399038",
        "terminal": "BLCT3",
        "voyage": "FK243A",
        "vesselDirect": "E",
        "tradeFlag": "W",
        "vesselReference": "MSCET1030",
        "imo": "1",
        "vesselSysid": "0",
        "vesselOwner": "MSC",
        "vesselAgent": "PEN",
        "serviceCode": null,
        "lineOperatorCode": "MSC",
        "ctnStartTime": "2022-10-26 00:00:01",
        "ctnEndTime": "2022-10-31 00:00:01",
        "hazardStartTime": null,
        "hazardEndTime": null,
        "spHazardStartTime": null,
        "spHazardEndTime": null,
        "etaMonthly": "2022-10-30 14:00:00",
        "etdMonthly": "2022-10-31 00:00:01",
        "etaRecently": null,
        "etdRecently": null,
        "etaDaily": "2022-10-31 16:30:00",
        "etdDaily": "2022-11-01 14:00:00",
        "eta": "2022-10-31 16:30:09",
        "etd": "2022-11-01 14:00:00",
        "etanchor": "2022-10-31 00:00:01",
        "atanchor": "2022-10-31 00:00:01",
        "ata": null,
        "atd": null,
        "ats": null,
        "ate": null,
        "ets": null,
        "ete": null,
        "voycloseTime": null,
        "customCloseTime": "2022-10-31 04:30:00",
        "portCloseTime": "2022-10-31 04:30:00",
        "berthReference": "10",
        "ports": "AEJEA: INNSA: CNFOC: ZADUR: IQUQR: IRBND: BRSSZ: BRPNG: ARBUE: UYMVD: BRRIG: SGSIN: BRNVT: HKHKG: OMSLL: ESVL1: ESBCN: ESVLC: ITGIT: ITSPE: MTMAR: FRFOS: CNCWN: ITGOA: SADM1: LKCM1: IQUQ1: AEJE1: SAJU1: INMU1: QAHM1: QAHMD: AEAUH: CNSHA: AEKH1: AEAU1: SAKAC: KWSAA: CNSHK: INNS2: INNS1: LKBUT: INMNB: MYTPP: LKCMB: SADMM: SAJUB: INMUN",
        "lastPortCode": "CNSHA",
        "nextPortCode": "CNSHK",
        "lastPortName": "上海",
        "nextPortName": "蛇口",
        "voyagePublishTime": null,
        "voyagePublished": "Y",
        "publishTime": "2022-10-25 09:22:57",
        "published": "Y",
        "modifyCode": null,
        "modifyRemark": null,
        "vesselOwnerCtnTimes": null,
        "status": "Y",
        "vesselAgentName": "外代",
        "etaBegin": null,
        "etaEnd": null,
        "ataBegin": null,
        "ataEnd": null
      }
    ]
  }
}